{
   "files": [   
 {
         "name": "1.SPKTH-01-VIP",
         "url": "https://raw.githubusercontent.com/minnersf5/Spkthz/main/VIPSPKTH1.ovpn"
      },



{
      "name": "2.SPKTH-02-VIP",
         "url": "https://raw.githubusercontent.com/minnersf5/Spkthz/main/VIPSPKTH2.ovpn"
      }
      

   ],
"message":"\n✨รองรับซิม True,Dtac โดยไม่ต้องมีเน็ตในซิม✨ \nUnlimitedSpeed NoNetSimCard \n.\n🆕Update By = Mean  ",
   "title":"🔥ไฟล์อัพเดทใหม่พร้อมใช้งาน แตะที่ปุ่ม...UPDATE...🔥" ,
   "version": 1.2
}
