{
   "files": [   
 {
         "name": "Dtac​ Free SG01",
         "url": "https://raw.githubusercontent.com/Nknooker/Nknooker/main/Dtac%20Free%20SG01.ovpn"
      },




      "name": "Dtac​ Free SG01",
         "url": "https://raw.githubusercontent.com/Nknooker/Nknooker/main/Dtac%20Free%20SG01.ovpn"
      },
      

   ],
"message":" \nรองรับ NOPRO Dtac  True​\n​DTAC​ NOPRO\n​TRUE​ NOPRO\nเซิร์ฟเวอร์ไม่แรง\nต้องขออภัยมาใน ณ ที่นี้ด้วยครับ\nเคดิตไฟล์ Addmin kan\n คอนฟิกเวอร์ชั่น: 2.1 \nอัพเดทเมื่อวันที่: 06/ตค/2022\n \nผู้พัฒนาแอพ:NOOKER\n  ",
   "title":"ไฟล์อัพเดทใหม่พร้อมใช้งาน" ,
   "version": 1.1
}
